angrcli/__init__.py
angrcli/py.typed
angrcli/ast/__init__.py
angrcli/ast/rendering.py
angrcli/full/__init__.py
angrcli/interaction/__init__.py
angrcli/interaction/explore.py
angrcli/plugins/__init__.py
angrcli/plugins/explore.py
angrcli/plugins/watches.py
angrcli/plugins/ContextView/__init__.py
angrcli/plugins/ContextView/colors.py
angrcli/plugins/ContextView/context_view.py
angrcli/plugins/ContextView/disassemblers.py
angrcli-1.2.0.dist-info/LICENSE
angrcli-1.2.0.dist-info/METADATA
angrcli-1.2.0.dist-info/WHEEL
angrcli-1.2.0.dist-info/top_level.txt
angrcli-1.2.0.dist-info/RECORD
