Metadata-Version: 2.1
Name: angrcli
Version: 1.2.0
Summary: UNKNOWN
Home-page: https://github.com/fmagin/angr-cli
License: MIT
Platform: UNKNOWN
Requires-Python: >=3.6
License-File: LICENSE
Requires-Dist: angr
Requires-Dist: Pygments
Requires-Dist: cmd2
